quri_parts/qsub/NOTICE
quri_parts/qsub/allocate.py
quri_parts/qsub/codegen.py
quri_parts/qsub/compile.py
quri_parts/qsub/eval/__init__.py
quri_parts/qsub/eval/gatecount.py
quri_parts/qsub/eval/qubitcount.py
quri_parts/qsub/eval/quriparts.py
quri_parts/qsub/evaluate.py
quri_parts/qsub/expand.py
quri_parts/qsub/lib/__init__.py
quri_parts/qsub/lib/py.typed
quri_parts/qsub/lib/qpe.py
quri_parts/qsub/lib/std/__init__.py
quri_parts/qsub/lib/std/_namespace.py
quri_parts/qsub/lib/std/cnot.py
quri_parts/qsub/lib/std/conditional.py
quri_parts/qsub/lib/std/control.py
quri_parts/qsub/lib/std/cz.py
quri_parts/qsub/lib/std/inverse.py
quri_parts/qsub/lib/std/logic.py
quri_parts/qsub/lib/std/measure.py
quri_parts/qsub/lib/std/multi_control.py
quri_parts/qsub/lib/std/multi_control_gates.py
quri_parts/qsub/lib/std/multipauli.py
quri_parts/qsub/lib/std/rotation.py
quri_parts/qsub/lib/std/single_clifford.py
quri_parts/qsub/lib/std/swap.py
quri_parts/qsub/lib/std/t.py
quri_parts/qsub/lib/std/toffoli.py
quri_parts/qsub/link.py
quri_parts/qsub/machineinst.py
quri_parts/qsub/namespace.py
quri_parts/qsub/op.py
quri_parts/qsub/opsub.py
quri_parts/qsub/param.py
quri_parts/qsub/primitive.py
quri_parts/qsub/py.typed
quri_parts/qsub/qubit.py
quri_parts/qsub/register.py
quri_parts/qsub/resolve.py
quri_parts/qsub/sub.py
quri_parts/qsub/trans/__init__.py
quri_parts/qsub/trans/qp_trans.py
quri_parts/qsub/trans/transpiler.py
quri_parts/qsub/visualize.py
quri_parts_qsub-0.24.1.dist-info/LICENSE
quri_parts_qsub-0.24.1.dist-info/METADATA
quri_parts_qsub-0.24.1.dist-info/WHEEL
quri_parts_qsub-0.24.1.dist-info/RECORD
