Metadata-Version: 2.1
Name: quri-parts-qsub
Version: 0.24.1
Summary: A support library for consturcting structured quantum circuits
Home-page: https://github.com/QunaSys/quri-sdk
License: Apache-2.0
Keywords: quantum,quantum computing
Author: QURI Parts Authors
Author-email: opensource@qunasys.com
Requires-Python: >=3.10
Classifier: License :: OSI Approved :: Apache Software License
Classifier: Programming Language :: Python :: 3
Classifier: Programming Language :: Python :: 3.10
Classifier: Programming Language :: Python :: 3.11
Classifier: Topic :: Scientific/Engineering :: Physics
Classifier: Typing :: Typed
Requires-Dist: qulacsvis (>=0.7.6,<0.8.0)
Requires-Dist: quri-parts-circuit
Requires-Dist: quri-parts-qulacs
Project-URL: Documentation, https://quri-parts.qunasys.com
Project-URL: Repository, https://github.com/QunaSys/quri-sdk
